gzeus-0.1.1.dist-info/METADATA
gzeus-0.1.1.dist-info/WHEEL
gzeus-0.1.1.dist-info/licenses/LICENSE.txt
gzeus/chunker.py
gzeus/utils.py
gzeus/__init__.py
gzeus/_gzeus.pyd
gzeus-0.1.1.dist-info/RECORD
