Metadata-Version: 2.3
Name: gzeus
Version: 0.1.1
Classifier: Development Status :: 4 - Beta
Classifier: Programming Language :: Rust
Classifier: Programming Language :: Python :: Implementation :: CPython
Classifier: Programming Language :: Python :: Implementation :: PyPy
Classifier: License :: OSI Approved :: MIT License
Requires-Dist: typing-extensions ; python_version <= '3.11'
License-File: LICENSE.txt
Keywords: compression,data-processing
Author-email: Tianren Qin <tq9695@gmail.com>
Requires-Python: >=3.9
